<?xml version="1.0" encoding="utf-8"?>
<ScrollView xmlns:android="http://schemas.android.com/apk/res/android"
    xmlns:tools="http://schemas.android.com/tools"
    android:layout_width="match_parent"
    android:layout_height="match_parent"
    android:fillViewport="false">

    <RelativeLayout
        android:layout_width="match_parent"
        android:layout_height="wrap_content"
        tools:context=".selectdiet">

        <ImageView
            android:layout_width="match_parent"
            android:layout_height="300dp"
            android:contentDescription="@string/todo"
            android:src="@drawable/an1"
            tools:ignore="ContentDescription" />

        <ImageView
            android:layout_width="match_parent"
            android:layout_height="300dp"
            android:layout_marginTop="300dp"
            android:src="@drawable/an2"
            tools:ignore="ContentDescription" />

        <ImageView
            android:layout_width="match_parent"
            android:layout_height="300dp"
            android:layout_marginTop="600dp"
            android:src="@drawable/an3"
            tools:ignore="ContentDescription">

        </ImageView>

        <ImageView
            android:layout_width="match_parent"
            android:layout_height="300dp"
            android:layout_marginTop="900dp"
            android:src="@drawable/an4"
            tools:ignore="ContentDescription">

        </ImageView>

        <ImageView
            android:layout_width="match_parent"
            android:layout_height="300dp"
            android:layout_marginTop="1200dp"
            android:src="@drawable/an5"
            tools:ignore="ContentDescription">

        </ImageView>

        <ImageView
            android:layout_width="match_parent"
            android:layout_height="300dp"
            android:layout_marginTop="1500dp"
            android:src="@drawable/an6"
            tools:ignore="ContentDescription">

        </ImageView>

        <ImageView
            android:layout_width="match_parent"
            android:layout_height="300dp"
            android:layout_marginTop="1800dp"
            android:src="@drawable/an7"
            tools:ignore="ContentDescription">

        </ImageView>

        <ImageView
            android:layout_width="match_parent"
            android:layout_height="300dp"
            android:layout_marginTop="2100dp"
            android:src="@drawable/an8"
            tools:ignore="ContentDescription">

        </ImageView>

        <ImageView
            android:layout_width="match_parent"
            android:layout_height="300dp"
            android:layout_marginTop="2400dp"
            android:src="@drawable/an9"
            tools:ignore="ContentDescription">

        </ImageView>

        <ImageView
            android:layout_width="match_parent"
            android:layout_height="300dp"
            android:layout_marginTop="2700dp"
            android:src="@drawable/an10"
            tools:ignore="ContentDescription" />

        <ImageView
            android:layout_width="match_parent"
            android:layout_height="300dp"
            android:layout_marginTop="3000dp"
            android:src="@drawable/an11"
            tools:ignore="ContentDescription" />

        <ImageView
            android:layout_width="match_parent"
            android:layout_height="300dp"
            android:layout_marginTop="3300dp"
            android:src="@drawable/an12"
            tools:ignore="ContentDescription" />

    </RelativeLayout>
</ScrollView>